TemporalGeneralizedRules/AssociationRule.py
TemporalGeneralizedRules/Database.py
TemporalGeneralizedRules/HTAR.py
TemporalGeneralizedRules/HTAR_utility.py
TemporalGeneralizedRules/PTT.py
TemporalGeneralizedRules/Parser.py
TemporalGeneralizedRules/__init__.py
TemporalGeneralizedRules/apriori.py
TemporalGeneralizedRules/cumulate.py
TemporalGeneralizedRules/cumulate_utility.py
TemporalGeneralizedRules/rule_generator.py
TemporalGeneralizedRules/tgar.py
TemporalGeneralizedRules/utility.py
TemporalGeneralizedRules-1.0.2.dist-info/LICENSE.md
TemporalGeneralizedRules-1.0.2.dist-info/METADATA
TemporalGeneralizedRules-1.0.2.dist-info/WHEEL
TemporalGeneralizedRules-1.0.2.dist-info/top_level.txt
TemporalGeneralizedRules-1.0.2.dist-info/RECORD
