Metadata-Version: 2.1
Name: TemporalGeneralizedRules
Version: 1.0.2
Summary: Algorithms for association Rule mining
Author: Ignacio Fernandez y Emiliano Galimberti
License: MIT
Classifier: Programming Language :: Python :: 3
Classifier: License :: OSI Approved :: MIT License
Classifier: Operating System :: OS Independent
Requires-Python: >=3.8
License-File: LICENSE.md
